sharnote.py
sharnote-0.1.0.dist-info/LICENSE.txt
sharnote-0.1.0.dist-info/METADATA
sharnote-0.1.0.dist-info/WHEEL
sharnote-0.1.0.dist-info/entry_points.txt
sharnote-0.1.0.dist-info/top_level.txt
sharnote-0.1.0.dist-info/RECORD
