Metadata-Version: 2.1
Name: sharnote
Version: 0.1.0
Summary: A command line note taking utility developed in Python that saves notes in JSON format
Home-page: https://github.com/sharadcodes/sharnote
Author: Sharad Raj Singh Maurya
Author-email: iamsharadraj@gmail.com
License: UNKNOWN
Platform: UNKNOWN
Classifier: Programming Language :: Python :: 3
Classifier: Programming Language :: Python :: 3.6
Classifier: Programming Language :: Python :: 3.7
Classifier: License :: OSI Approved :: GNU General Public License v3 (GPLv3)
Classifier: Operating System :: OS Independent
Requires-Python: >=3.6
